[
    "{\"Year_Month\":\"2016/07\",\"Immigrants\":1328974,\"Immigrants_rank\":1}",
    "{\"Year_Month\":\"2016/08\",\"Immigrants\":1160455,\"Immigrants_rank\":2}",
    "{\"Year_Month\":\"2016/09\",\"Immigrants\":1125245,\"Immigrants_rank\":3}",
    "{\"Year_Month\":\"2016/06\",\"Immigrants\":1080648,\"Immigrants_rank\":4}",
    "{\"Year_Month\":\"2016/10\",\"Immigrants\":1050757,\"Immigrants_rank\":5}",
    "{\"Year_Month\":\"2016/04\",\"Immigrants\":1042752,\"Immigrants_rank\":6}",
    "{\"Year_Month\":\"2016/05\",\"Immigrants\":1042120,\"Immigrants_rank\":7}",
    "{\"Year_Month\":\"2016/12\",\"Immigrants\":991505,\"Immigrants_rank\":8}",
    "{\"Year_Month\":\"2016/03\",\"Immigrants\":939031,\"Immigrants_rank\":9}",
    "{\"Year_Month\":\"2016/11\",\"Immigrants\":904804,\"Immigrants_rank\":10}",
    "{\"Year_Month\":\"2016/01\",\"Immigrants\":865969,\"Immigrants_rank\":11}",
    "{\"Year_Month\":\"2016/02\",\"Immigrants\":696579,\"Immigrants_rank\":12}"
]